bai_lockbox-0.0.5.dist-info/DESCRIPTION.rst
bai_lockbox-0.0.5.dist-info/METADATA
bai_lockbox-0.0.5.dist-info/metadata.json
bai_lockbox-0.0.5.dist-info/RECORD
bai_lockbox-0.0.5.dist-info/top_level.txt
bai_lockbox-0.0.5.dist-info/WHEEL
lockbox/__init__.py
lockbox/exceptions.py
lockbox/parser.py
lockbox/records.py
