Metadata-Version: 2.0
Name: bai-lockbox
Version: 0.0.5
Summary: A library for parsing files in the BAI lockbox format.
Home-page: https://www.github.com/FundersClub/bai-lockbox
Author: Jon Friedman / FundersClub Inc.
Author-email: jon@fundersclub.com
License: Apache License 2.0
Platform: UNKNOWN
Classifier: Development Status :: 3 - Alpha
Classifier: Programming Language :: Python :: 2
Classifier: Programming Language :: Python :: 2.7
Classifier: Programming Language :: Python :: 3
Classifier: Programming Language :: Python :: 3.4
Classifier: License :: OSI Approved :: Apache Software License
Classifier: Intended Audience :: Developers
Classifier: Intended Audience :: Financial and Insurance Industry
Requires-Dist: six
